ekuiper/__init__.py
ekuiper/function.py
ekuiper/sink.py
ekuiper/source.py
ekuiper/runtime/__init__.py
ekuiper/runtime/connection.py
ekuiper/runtime/context.py
ekuiper/runtime/contextimpl.py
ekuiper/runtime/function.py
ekuiper/runtime/plugin.py
ekuiper/runtime/reg.py
ekuiper/runtime/shared.py
ekuiper/runtime/sink.py
ekuiper/runtime/source.py
ekuiper/runtime/symbol.py
ekuiper-2.3.0.dist-info/licenses/LICENSE
ekuiper-2.3.0.dist-info/METADATA
ekuiper-2.3.0.dist-info/WHEEL
ekuiper-2.3.0.dist-info/top_level.txt
ekuiper-2.3.0.dist-info/RECORD
