Metadata-Version: 2.4
Name: ekuiper
Version: 2.3.0
Summary: Python SDK for eKuiper portable plugin
Home-page: https://github.com/lf-edge/ekuiper
Author: LF Edge eKuiper team
Author-email: huangjy@emqx.io
License: Apache License 2.0
License-File: LICENSE
Requires-Dist: pynng==0.8.1
Dynamic: author
Dynamic: author-email
Dynamic: home-page
Dynamic: license
Dynamic: license-file
Dynamic: requires-dist
Dynamic: summary
